{
  "resource_uri": "https://www.courtlistener.com:80/api/rest/v3/dockets/4444308/",
  "id": 4444308,
  "court": "https://www.courtlistener.com:80/api/rest/v3/courts/texapp/",
  "clusters": [
    {
      "resource_uri": "https://www.courtlistener.com:80/api/rest/v3/clusters/4277791/",
      "id": 4277791,
      "absolute_url": "/opinion/4277791/willis-drake-lafayette/",
      "panel": [],
      "non_participating_judges": [],
      "docket": "https://www.courtlistener.com:80/api/rest/v3/dockets/4444308/",
      "sub_opinions": [
        {
          "resource_uri": "https://www.courtlistener.com:80/api/rest/v3/opinions/4055052/",
          "id": 4055052,
          "absolute_url": "/opinion/4277791/willis-drake-lafayette/",
          "cluster": "https://www.courtlistener.com:80/api/rest/v3/clusters/4277791/",
          "author": null,
          "joined_by": [],
          "author_str": "",
          "per_curiam": false,
          "date_created": "2016-09-29T06:37:07.703940Z",
          "date_modified": "2017-04-16T05:56:43.685706Z",
          "type": "010combined",
          "sha1": "4274b1270dec392c92953478aa10d0862383498f",
          "page_count": 39,
          "download_url": "http://www.search.txcourts.gov/RetrieveDocument.aspx?DocId=103993&Index=%5c%5cOCA%2dPSQL01%2ecourts%2estate%2etx%2eus%5cTamesIndexes%5ccoa02%5cOpinion",
          "local_path": "pdf/2015/05/14/willis_drake_lafayette.pdf",
          "plain_text": "        r~·     1.·,\n\n\n\n\n    FROM;\n         •) RA.K E L•. WI L L1 S Jf ·1 S1S I3D\n         H. 1-1. [l) FF .1 f L 1~ UN I T - [a) C. lf\n        :lhlol FM jtJS Y\n        TEN tJ ES~ EE C:D LiJJJ :11 T)(. 1 S gg ~\n                                                                        RECEiVED t.N\n                                                                        ~OfCR~NALA~\n        ,                                                                    , MAY 14 2015\n      TO,\n         THE ~u.STIC..ES DF                                                  Abli AeoMl, Cfe!Fk\n              THE C.DURT 0 F CRIMIAJA.L A.PPEAL~                 ~\"::\n\n\n              P. o. ~DX 1:230~ 1 CA PI TfJ L ~TATIDtJ\n                                        ,·\n\n              AtJST7Al 1 TEXA~· 7B7//\n\n              R.E =                          --\n                       J:N·'EX. PARTE I)RAKE L, W!LliS1 WR-77,:J'-Ib-D7\n                       1: Ca CAU5E  .MD, FOR- .2'-IDjO- T (A & B) 1 IN THE\n                       1) IS T RItT C0 U RT 0 F ~ALL AS CO UN ,T !j.\n                            LETTER. MD TI.~tJ REB-IJE-5 TZI\\JG LEAVE TO\n                        F 1 L E A PET I           T I 0 N F 0 R A WR. IT DF N\\~1\\1 •)/\\MUS\n              TD Tf-tE H5/J.;         LDLJI~E        PEAASOtJt CLERk!\n              'NtJOU~ .YoU PLE:/\\~f_ I,JFOR_M IHE ttlUftr THAT [),J ~ECE.Mi?lfrQ\n              oz, ~oJJ       ,   ItJ THE A.~ovE JVuMBEREA CAu_sE                       nr:   Atr.roAJ,\n              TI-!A.T RELATO(( ''~AN~E•\\ OVER'' HI~ SLJPPLEMEAJ'TA.l APP-\n                                  ,\n\n              LitA.TiiJN J:QR A POST- CONVItfiD/J WR.II L)F HABEA~\n              CDR PuS ART. I Ia 0'1 ~ V~ A.~ C. C.4 P. TO TI-lE H~ H. LD r-~IEV~\n              U fJ IT - T r) [ Ll      1     d. wIa I ~ M 10 5-l/        I     IE N tJ E ~ S E E -\n                                                       ~~Jf I\n\n\n( cc)\n\f ,i_~\n\n\n\n\n            cDLD IJ ~ I       T EX A~ 7 5 g8 L/       I   PR I   ~b AI     A.IJ I H{) RIT 1 E~ F DR!. Mtrr.-\n            LIJJG ·r<EL-A. T/J R' ~I ·~EC.E.M.SE~\n                         11                                            {)}}I   dDIIJ 5UPPLEMEtJ1Al 1\\PPL-\n            I t:ATIDAJ ~DR. A.. P~) T- CON                   vrc_ T ~{)N            ~JR.I.T   nr:   /~A~EAS [JJ~-\n\n             Pus II.D1 1 WA.S           A~~.\\   R£SSE 1) TD THE •~I~TRILT L.LER.K CJF TUE\n            d.&3rd tru•LLL.IAL '1ISTRitT                   uurtr oF                ~lALlA.~ t6UAJT:J, 'JA.LL-\n            AS        I TE~A~   75j{J7     I    TUE LOUQT OF (-{IS C..fJI\\JV:ZLT IlJtJo J>F1£Je\n            TJ-lf: ~ LJ B M 1 -~S IDIJ ~ATE           OF FE g R.uA~~ J l1 aDll-                  tJF ({ELAIDR~   '\n                                                                   '\n\n            D rti.bi.NAL PDSI- [DI\\JV ItT IO/'J WRIT 0~ t:-tA.f&fAS [IJ(J.,_(Ju~\n            1f,rJ7, DN iJEL.ENL~Ert tJ'i, .2ol(- RELATDRs JuPPLfM&JrAL APPLI-\n            L-kT IOAJ rDQ          A.    Posr- LO!'J\\JftTID.\".J\" W{('f1              ~r-   1-JA(!EAS LDf{.fJuS\n            1/.07~ WAS \\'TI/t'\\fl~'\\\\ flA\"P\\£t\\ lJVEA. ID PRTIDrJ AU1HIJR.IT1ES.\n                      IT l-lA.~ PAS~E'\\ ~ /:2 ~EARS SII\\JC.E RELATD~'~ '~E(fM~ER.\n                                                  1\n\n\n            OS ' ciOil- SLJ PP LE AAEJJT AL A. PPLILA. TIDJJ IJF J.iABEM                            [l)R.Pu~ I L011\n\n            HAS SEEAJ 1-tArJ)\\Ei~ OVER TO THE --PRI5DtJ A.tJfHDRIT1~~ F\"lJR\n            NLA1L rJJb. IWE rR.rAL tbu~r aF RELA.To((') toi\\J vrL fiDJJ\n            CbULt\\ AJ 0 T MA.KE 1\\. F ItJ 1\\ I.rJ (;S 0 F FALT~ A.f\\/1\\ ClJ.JJ CLtJ~WrJ\n\n            OF LA.W TJ..\\R.OlJG~ E.VIr\\t.rJTIA.~ i-tEA.R.IrJb 1 As QE.~tJIR.E•\\\n                                    '                                                                   \\\n            B~ V,A., t.CP.        AR.T# /Lt)7, BEL/\\US.E TRIAL [{)Ut( ~L·)IJT RE-\n            CE.LVE Tl~f PETITilJtJ I ·:)o TlJ NO F~lJLT                                    OF QE:L/\\IQ~S OWA11\n            w11 T Lt4 LEA.VE ~ REL/\\TDQ ~JITH tJ () MLES~\n                                                                               1\n\n                                                                                              10 1R.TAL [DoR1.''\n                                                          P9/~c2\n\nrcc)\n        '\n            •'.:·,:\n\f .'-~...\n\n\n\n\n           A~ tJt= Tt-lf S.U~MIS~IO/\\J •\\ATE 01=\" 11-liS LETTErQ. Ml!J·r:rDAJ\n           Rt&UE~T       I.rJG LEA..\\JE TD -~1 LE A PETIT IDJ\\J FOP.. A. Wf<..IT OF\"\n                                                                      ,,          ,,\n           MAtJ1\\AMU~' RElf.\\/OR. HAS, UDI RECEIVE~\\ IJ011Lf, THAT\n           1-tr~ ')ELEM~ER. b~, ~DU,            SuPPlE. MENIAL APPLit.AT1DtJ FoR.\n           Pos-r . .   C.DAivrc_ TIDtJ WRJ:T ·i..tA~EA~     c.or<..Po1 tL07,     WA.~   EITHER_\n\n           Tr{AJJ~ MI i fE I~ T{) THE lt<IAL CDUR.T I D((            ID THI!) CDIJ{(T\n           AS M.rvJi)A.TEi\\ g'j LA.W        1   Af\\Jt\\ RELATOR \\.JILL          ~1-\\DW THE\n           FOLLDWI/\\JG:\n                                            STATU£:\n               'THE PURPD~E DI= A.. WRIT ll F HA~EAS [JJQ. PtJ~ I~ TD D~TAitJ\n                                  I\n\n\n           A .SPEE~~ A.f'JI\\ EFFf.C..Il.V£ A•\\;!u;\\ICAi:!.IJN          nr ~ PtR~OI\\J\\\n           f<I[;l-lT TlJ LIBERATI/JN rRDM ILLEbAl Q.E~TA.A.IAJT. Ti-lE VEr'<~\n           PuR.PDSE DF Ti-\\E WR..IT [) r: HABEA~ toRPU S IS 1D ~AFE&UARt)\n                          '           .                                    .\n           A PER.~OAJ ~ FREEt)lJM. FROM ;~ETE/JT.IOAJ IN VItJLATIDAf tJF\n\n           CDAJSTITUTID/\\JA.L             6UARAIJIEE~.      TI-lE PuRPL)S£ OF THE WRIT\n           OF HA.&E.A~ tDRPU ~ I5. TD CJ~ TAirJ A SP£E•) ~ A.:\\Ju 1\\IC.A.T10Al\n                              '                         .                          .\n           ~FA PER~OAJS           R1bHT fD LI~f.RA.T!oAJ FRIJM ILLEGA.L RE-\n           .STRAIMI.\n                             CITlN6 CA~ES:\n           SP6TV.I LLE v~ LAitJ I ILiCI Fo 3d 3741 _11g f5rh Ctr. jqqg).\n                                            P«J:#~\n\n\n(c. c)\n\f.,..-;:;-,'\n\n\n\n\n                   c.ooPE~ v~ ~R.ooKSi-\\IR..E, 10 r.3d j77,J7Cf                            fs-rh cu~      1qq5).\n                   1-tOU.SI[)/J V~ L~C..I<     1   42,7        u, S.   JftJfo, IDg 5al!:+. :J37q,/DI LEd.\n                      ~4s ftqggL\n\n\n              I.   ~~~EA:S L.O((.f>US f{E ~ brD5, l\n                                                                                                     II         ,,\n\n                        HA.r:1EA~ tD~~U ~ PET ITIDtJ                    s HCJUL·~    ~E ~EtN\\.£.'1 FILE•\\\n                   WHErJ PETIT IDJJ I~ HM,\\E'\\ 0\\JE({ TD P((ISO/'J ~u-n-\\O({ff:IE~\n                    FOR NLA.I L 7.1Jb .. J2 U• S, C. A~ § J !l5 tt o\n                         A 1-\\A.~EA) PET1T1DN 5HDuL'! f1E •1EEJAE•\\ FZ:LE:'l WHEAl THE\n                   PEIITID.AJ IS.         HAN•1E 1~ OVE:ft ID PR.I~ON AUTI-lfJR.ITIE~ FDR..                          N\\A-\n                   .ILI!Jbo SIMILA.QL'1                1   IN C.DlJ PER V. ~Rnr,KjJ-\\If<.E                1   7D L3d\n\n                   37713 7q t.5rh C.lr. f£1.QS)            1   \\JE l-IEU\\ THAT A PR.D SE PAl.SDNER\n                   LIT7GA.rJI~ LDMPLA1/JT I5 FILE') AS 5DDA1 A.~ THE PLEA.~IrJ{,S\n                   MA.VE ~EE/J •\\£Pl)-SITE•} INTD TI4E PRI5DN MA.1L S~~ TfM o IAJ\n                   J..IDUSTDN      v,   L/\\c.l<,   yg7 u.s.            J.foitJJJDg   s.t+. 237q,Joi           LEd~1d\n                   ~Lis (Jqgg)          wHrti-f tSTA~L15E;\\ A. ~IMILAR.                                   BD'i ~uLE'\\\n                                                                                               1\n                                   1                                                           MA1L\n\n                   J:DR '~E T ER..MIN :ttJ f:J WHEAl I\\ PR.O .SE ND rItE dF APPEAL F({OM\n                   i)TSM.IS.SAL DF          A 1-\\1\\{jEA~ ALTIDrJ WDiJU\\ ~E CbN~I~Ef<.E,1\n                   rrte.·)   &   TtJ 1-ltJuSTDN T!4E             r_ouR.r    P£LD6JJ1Zt'~ ntA.T, [uJI\\I-\n                   Jk!LLE 1\\ TJ\\1 LA.W1 UNA.I•\\E1\\ ·~~ CDUI\\JSEL                       1   A!\\JA   UIJA~LE 1'D\n\n                   LEA..VE. THE PR.l.SOJJ          1   A PRlJ sf Pf<.r.~DNER.S CtJJJf({DL lJVE.Y<-\n                                                                 P9. 4* 4\n\n(( c\\\n\f. ,.\nI\n\n\n\n\n            TI-lE PRDC.E.)SING Ot= HTS IJDIItf. 1\\JEtESSAR.!Ltj C.EA.5E.5>\n            As, _t;DDN A~ HE 1-\\A.I\\/1~ S IT ~ VE.fZ [,.] ~d\n                                                                            \\\\\n                                                                                     .·a+ j~fo,\n       d. C.DtJSTITIJ11DI\\!Al LA-W I<E!.i3a8\n             PRISOtJ KE~ 4 (ID.J)\n                AIJ A.PPL1C..AtJT Fo·~               1-H~~Eh~      CDR-PuS f<El1£F                 t.-\\A~   A. C.DAJ-\n                                               .                                       .\n\n             ~TITUTTO/\\JAL          RIGHT TO ACCES<::, ID COURT~ ~~ WELt A.S A\n             STATUfDRY R.IGHT TD FILE A.tJ                                ~PPL'ftAT.!O/'J            FOR 'NfUT\n             DF HA~EA~ CDr<.Po~ WITH T~E, 'JISTRILT CLEf<.K~ VERJJDIJS\n                                                                      .          '\n             ANIJ~ TE'XA.~ C.DN~ T.,           .1\\RTe> 1,   ~ l~ // \\fER.t,JDI\\J~     Af\\JrJ •.   TcxA.~    C. C. P.\n             ART~ f LD 1   I   ~   3 (b)   0\n\n\n\n\n       3o M.J\\ 1\\J ~ J\\ MUS KE ~ .3 {o'!al) I J~\n                 M./\\1\\Jt\\/\\MU~ RELIEF Mf\\\"3 BE bf<.MJTE 1\\ IF T~E REL/\\TOIQ.\n            SJ-\\DW ~ fl) Tl-\\~T THE 1\\Cf _soubHT 1D ~E C.bM.PELLE~~ 1.~\n                                                                     --\n            PUR.ELY MI.tJISTf.RIAl1 A.f\\Ji\\ (~) TJ..lA.I THEf<.E I~ AfD A.r\\E&-\n            UAT E REME '\\ ~ A. T LA.W,\n\n       4.    MAJV ;\\A.Nlu S kEY ID\n                 A RELATOR ~EEKII\\Jb f\\AA..r-,Jl\\1\\MU~ RELIEF NlUSf HAVE A\n            C.LEA(( RibHT TD THE RELIEF .SD£JGi-IT1 AfltAI\\fTrJb /flAT TI-lE\n            ME A.I T S t, F TJ-IE A. E. L.1EF Si;tJ[_,Hr ARE ~E ~OAJI) '~1~ PiJ TE / Ti-\\E\n            RE.&tJIREMEtJT DF A. C.LEA.R. LEbA.l RieHT 1\\fElE ~~ITATE~\n            TI-l f\\T TI-t E LAW PLt\\:ItJL lj 1~ E ~U{1 BE~ THE ~U T:1 ID r6E PER FDRA'lE1l ~\n                                           P.9g At 5\n\f SUC.f-l Tl-lAT Tlif({E I~ NO RODM I=\"DfZ fHE EXEA.l:I~E OF\n t\\:r~tRE T IOI\\Jt\n\n      PuR_)UA.rJT ID THE ORI.GI!VAl d'URIS '~I C. T.IDIJ CJJ:\" Tf~IS\n[{)UQT   I   RE LA.TO (( Pf<.EVIOtJ~LY 1='1 LEI\\ A. LFTTER. M.OfiDN RE-\n &ut~TirJ6 LEJ\\.VE TD FILE.                   f\\. PET Il1\"01\\l F()R.. A WR.IT DF\n /v'\\A.NI\\/\\M.U1 OtJ I=\"E~((LJJ\\.R!1 \\~1 JOIQ, Wirl-t RE&uE~f TO THIS\n                                 ~I           ,,                   <                    I\n COU({1 TO ~ D A..tJ ItJ&lJ.1R. ':1                INTO TliE AAATTtR. {) J: f<.ELATV~~\n ~~ELfM~ER. Dg 1 :WItt                5u PPLfM£1\\JTAL APPLILATIOtAJ        I=Df<. A PD~T-\n\n [DJJVIt TIDIJ WRIT DF 11A.~E/\\~ C.DRPUS· A~T6 i L07' \\1../l...C..C..P.\n (SEE. RELI\\IDRS 1\\TTAL.HEI\\                 E~ HI BIT 1\\Jo.     I,' A1TALHE'\\   FEg:QuAA.Y\n I&, ~DIQ;'' MDI1DI\\J FDR. LEA.VE'') ( ~EE ({E.LATDR~ P\\TTA.LJlE 1\\ E'i.Hif!J:T\n ND.d., 1\\l\\f.LI!J q, btDI2, \"NlD11D!J r:o({ lE~VE'')         (sEE ri-\\1~ cDuR.T ~\n MARCH /ll, ~Dl~        I   fl   {jf<~ER_''/ FE~~lJM.~ A'1 I ~01~ •Jl{)({I\\E((\\' ,' JUIJE\n              '.1.~+                       1)EU:M~ER t-1, jol3 'drd tJDTILE\\').\n              1\n s, lD13,              NLYf1.LE'\\ /\n                                                                    1\n\n\n\n\n     DtJ ~r.JL~ ~ \\, ~oiQ i ~EC.EM~ER. 311 JDI~, Af\\J,·~ JV\\.ML~ j~~ J.Di4,\n ltELA.TDft A.TTA.L~\\E1\\ I\\ fR.uE C.DP~\n                                    Dr HIS ~ECEM~E({ fJ~, ~OIL ~uPP~\n LE:M.£rJTAL 1\\PPLlC.A.TID N WIZI.T nr Hf\\~EA:~ L.DR. PuS TD Hr~\n,clfTTE:~ M0110JJ FoR. LEI\\\\JE'\\~c..+. TO Ti-\\.I~ C.DUQT, f~EE: 1H1~\n tDuR.TS RE.LO((i\\~ tJ F RELAToR'~ •1£LEM~ER. {j~ 1 ciOlrL ~uPf. APP. ll~DI J.\nPREVI()u~L~ REtt\\.IOR. \\-\\1\\~ T1ME.L'1 r'<.E&CJE~TEI\\                   1HIS C.DU(J.:r-\n                                          pg/\"6\n\f,..   ,_\n\n\n\n\n                    i                      ·                               II·                ,,   ·\n           B1:1 :! T S JuRIS ~~I C. T :r D 1\\1             TD   1)   D AtJ II\\J tiU :r R.Y II\\Jm Tl~ E MAT-\n           TEr<s.   (JF       J.trs       :\\EL&vle:,E~ og, 2o~t, suPPLEMENTAL APPL1LArio!U\n\n           rorz urzrr or=                 t\\A~EA:~     CDttPu) Ito I 1 AN1\\ ALSo, TTMEL ~               RE&ue~Te'l\n           FDtt THI~ l.DUR.f To F.IL£ Tt-lE SA/IAE l-l~~EA~ {.f)(J_fJuS WIL!f 10\n           TI-\\E TR.IAL LnuRT ()~ HIS CDtJV.IL T.IDAle\n                RELATDR. FI LE.i\\ HI~ SUPPLE MEJJIAL .APPLI c_~ TibAl\n           ~Dr<.. J..ti\\~EA~ LDf<.PiJ~                f<E L1E.F AbA.!tJS r REAL PART j 0 F \\\n           TJJTEftE_ST ~ TAI£ 1~ UAJ•)Er< TEX.. [D~E C. RIM., PROC.. A/\\J/J. ARI.\n           ll~07 (sEE R.ELATD~S ATTA.tHE•\\ \\EtEM.fSEft lJgJa2Dll, ~uPPLE-­\n           MfJJTAL APPLIC.A.T:IDJJ wRIT ild)7, V.AJC.t:P.'L RElA5Drtl-tM•\\-\n           E•\\ 0\\IE.A. l-115 '~ELEmt3EfZ Dgr.2DlL .SlJPfL£Nl&JTAL t\\.P.PLILATIDJJ\n           lJR.IT 0       r     t-\\~~EA~ LDIQPLJS Af<.T~ 11\"01              1    TO Ti-lE H; Wt WFFIELd UNIT\n           Pfti ~ DAJ     AlJ fH Df<.I T1 E<; I=' DR.. MA:I LIN G AJ 1E~ RE LA.TO{(~ PETI-\n                                                                                 j\n\n\n                                                                           II            \\l\n           TICJJJ IS J-lA,,P\\E 1\\ DVE~,-HE HA~ Al/J [DJJTRD[ DVE({ THE                                      PR.O-\n           C.EJ..~ItJG OF 14IS PETi TiotJ DJJL£ IT~S t~J\\AJ 1\\E 1 \\ tJVE{(. H!i\n           [otJTfZoL C.EA~E ~ ~- RELA1oR                     Co\"rrt:tJ,li        1   Tl~AT HE I~       'TuJ.rJ-\n           .SI{ILLE~ AT LA..W                  i   iJNA.I'\\E1\\ ~~ lOUIJSE L I lJNA.~LE TD lEAVE\n           1-jiS PRI~OA) AtJ;) 1S 1rJ'11bEJJI lJHILl-1, TJ-IE Pr<DLES~r,vG oF\n           M.f.\\ILitJ& IS ~JJIIR.E~L~-l\\ UPoN Tf-IE (JQI~DtJ AuTf~DR.111E\\ ..\n                                      1\n\n\n\n\n(c.c\\\n\f  .\n  ;,.\\\n\n\n\n\n               0 tJ AP((1 L ~ 3 i .:2 oi 4 1 T 1-l E 1~, w,                 c.o FJ: IE v\\ uAJ r T ~s , tllA1 Lf<DDM\n         PRI~DtJ ~tJTI-\\DfZir~, M({~e ~O({~EY', INJ:OttN\\f•) RElftTbR.\n         Tf-IAT HE .LS MDT J\\.LLDLJEi~ TO HA.V~                                     A f_DPY   or-   fHE PRISOtJ\n         \"MA::r.L IJJb          lob\"        ItJ · ~J.. L!Jf0\\ WITH, ()lJgLIL ItJF[jftMA.fiOJJ\n         At T ~ EC. T \"1. DtJ 5 S j. D~g                      (a) (r)   1   D F T~E TE~A~ 60VER.JJ MEAJ T\n         C.IJt~E     I    WI-\\ILI-l ~fAIES~              II   A. GOVER/\\fMEN'fA.L gD•l'1 I~                 Mf)T\n\n         Rf&UI ({E'\\ 10 AC.C.EPI CJA. CDMPL~ WITH A QE~UES I FD(.{\n         IJJFtJf<.MATI.DN FRDM A.tJ TfJ 1\\IVI'\\UAL wl-\\0 IS !MPRI~­\n\n         D/'JE'l DR C.OI\\lFII\\JE'\\ ItJ A. C..tJR({ELTIONAL ~.1\\C.ILIIY.'\\\n                                                                                                     I\n               DtJ I\\Pl{1.L jy, J.Dit.J              I    TWE      t~LU.     [DFFIGU\\ UtJI.T.S ./YLAIL\n         ({(J{JfiL       l.Lf rtK   I   M{{~,   v.   SA LMOJ\\J      i   PR.I~Dill     AUTHDU T!iJ IiJ-\n         fO((M.E,) R£LA. TOil 1 Tt-\\AT THE PR.Ii;DJJ MA1 Lr.tJ(:, LOG ~HDIJS\n         ~.r.s •)ELEM~Ef<. tJ2. r ,1iJ ll , SuPPLEMEAJ1AL APPLILA.-riDAl FoR\n         A. PDSI·-Cbl\\lVILTlbl\\1                              W~IT      DF HJ\\r;EM C.CJR.Pu.S ART. lLtJ71\n         v~ A.t c.,c_l p, WA.~ PROtES~E·)                           Arv•\\ MA.ILE'l tJtJ •\\ELEM~Et<. L2J\n         ~Dll1 TD TUE ;~I~T RIL. 1 L.LERK1 fJF TliE ~23rcl Jt.P)IL.1AL •\\1S-\n         T~ILT C.Dua..T CJF ~/.\\LLA:) CDUtJTY 1 •) A.LL kS TE'il\\5 '15.:1011                                   \\JltrLH\n                                                                                i\n         .IS T~£ TRIA.L l.Durt.l OF REL~10i<.~ CDI\\.I\\f1LT10tJ J:OP... FIL-\n         IJJ b.,\n                                                              P9~~8\n\n\n\n(cc.l\n\f   .\n   ·~\n\n\n\n\n           . REJ~TDR. Wt\\S L-1 r-jEE•\\ DF MA.\"fEftiA.L EVI•\\EtJ(f 10 MAl.<E\n        A. ~({_£ PRDPER S~DWIJJG ~~ LE£-:,AL ~{)(JJMEtJTA.11DiJ fO\n        n\\r.\\ C.DoftT ,       mA.r   i-\\E 1-fAN,)E•\\ DVEI{ HI~ 1\\EL~M~E({ ts&, 1D IL\n        .suPPLEME/JTAL APPLil.A.T1DI\\f                  Po~T-WNV!CfiDAJ Wft1T        DF=\n        HA~EA.~ C.ORPUS AR'f, 11.07          1   TD THE PR1JOIJ ALJft4lJR.1T1ES fOR.\n        MAILIJJG,(SEE R.EL~1DfZS A'ff/\\C.I-tE 1\\ E~ H!BIT MD· 4 ).\n               A~ PR.E\\fibUSL~ ~~ISC.U.SSE 1L A P~D Sf Lii.!6~rJT ll~A.IS\n        [U]N..SKILL£~.1) ItJ LA.W./ UNJ\\1'~£'l B~ COUI\\ISEL1 U~~BLE fD ~EA.VE\n\n        1-\\I~ PRI-~DtJ   I   t<N 1\\ 1tJ 1~1&EtJf I I-lA~ 1\\Jb [(JAJf({f)L lJVER. HI_) PEI-\n        I. TION DJJC...E IT t-\\1\\.~ l?:,EE/J 1-\\AtJI)t•\\ DVER TD /HE PtLI~DJJ f.\\U-\n\n        THlJR.ITIE.S FDR MA.ILI(JB               a   WI-\\EJJ f\\ PR.O SE L1T1GfvJT \\-tAJIJl\\S\n        DVEf.J.. l-\\IS PETITIDtJ TD THE PfZI_SDN AUTH~R.ITIE~ FoftM.tUL-\n        ItJ6' Hrs PE1ITIOJJ            SHDolJ\\ BE ~~EENLE•\\ ,;FILEft. T~E PfZntEsUNG\n           .                                                      '\n        AtJ•\\ M.AILitJb Of:' T~E PR.D ~£ LIT1GMTS PET.1T1DJJ ~~ ff.IE\n                                                                                       .\n\n\n\n\n        PR..I.~D/J AUTHO((ITIE~ FDR Nlf\\ILI!Vb\" IS> THEr<.EFD{(E\"CbtJ~\n        SI '\\E~t:~) A M1JJ1S TEitAL '1U1~ ~y .THE P..ULES £J ~ At A. Af\\ft\\\n        Ti-lE T•)C.J PRISOJJ M/\\1L S~.SfEifl, M.A1L1rJb GUI 1JE/J ·THUS,\n        T~E FrfZ~ T RE&tJIREM.£1\\Jf F'OR .M/\\1\\f!\\A:M.U~ RELit=~· I~ FuL-\n\n\n\n\n( cc)\n\f  .\n  ·~\n\n\n\n\n       , ~ILLE•\\,\n                    11\n                         Tl{EflE :I.S NO PRDV.ISIOtJ FD(( A.rJ APPEA.L C..DtJ-\n        CEA-1\\JIJJG TI--\\E PR!.~DAI A.U IHDRI TIES MAIL S ~S TENt ftJ\n        PE~ FDR.M Tl-\\E t~lJ T Y lJ F PRlJL.E )SIAJG A.!J 1\\ M.~I L 1·tJ6          A\n                                                  '\n\n\n\n                                \\\n        IDtJ r T D THI; TtQ.IAL [()U f.L T     0 F 14 :IS [0/J VIt.. T1DrJ FD\\R.. F1litJ6.\n        '' TI~E IJJ A.B1 LIT .'1 TD A.PP EAL LEAVE.~ RE L~ fD R W11l-\\ JJ 0\n        A'\\E13..UA.IE REME:·~Y A.l LA.W~' TI-\\Er<EFDR.E               1   RELA.TDR \\-\\A:.~\n        Mt:T /HE _sE[t)tJa\\ R.E&U.! RE/VI.EtJT FDR M.AAI 1\\AMUS RELIEF.\n        ALL R.Ei1UIR.EME/'JTS ~DA. MA.rJ 1\\AMUS RELIEF 14\"-VE BEE tJ\n        FuLFILL E1\\         e\n\n\n            Ti-tE T Ei. CO 1\\ E .C. R.:rM ~   PRDt.* 1 AR.T. II tD4 {t~ EVE A.~ PAn V.r ~­\n       IDtJ RE.LAT IiJb TD \"THE WRIT DF                    HA.~E~ C.~&PuS         Si-IALL\n        BE MnST .rA.VDRA~LY Ll.HJSIRUE 1\\ II\\J iJR•\\ER TD 61VE\n       EFF £L r     -ro     THE R.EN\\E') ~, A.!'J1\\ P({o-rEc r THE         R.IbHrs o~\n       THE PER..SDI\\J _!;EEI-\\II\\JG RELIEF UAJ1\\ER.1T'\\)/ )Ef E~PARTE\n                                                                                  1\n        KERR.1 ~4 ~1Wo 3d t.f(4,4fq (TE~, CR!Ail. APPi JDD:J)( l/l-l£\n        PuRPO~E OF\"~ wRIT OF l~AaEAS C.lJR.Pu~·IS, TD OBTA1A1\n\n        A S PEE,) Y A 1\\J 1\\ EF~ ELT 1 VE A i\\          uu .1 CA.I 1: D1\\J 0 F A PE~-\n                                                            1\\\n\n\n\n\n(eel\n\f                                '                                       '\n\n\n\n R.E~-rR/\\'11\\lT:\\) (CitiNG &Lf\\l.KLE~[,E: V.l\\lllSDiJ,43l iJ,5d~3i\n71 1 q7      5. Lt. 1fLJ:;. 1, S:i L. Ed. jd t3h flqq7 \\ ( \"[T] 1-\\\"E' V£R~ PuRPD~E\nOl= THE WRII Di= \\4~~EA~ ttJR.PLlS ·~~ 'TD SA.FEGUAR.1\\ A 9ER-\n _soJJ~ FREE~lJM FRDNt ;\\ETEI\\fTTOtJ~ .uJ VIDLAT I{ji'J DF C..DJJ~I-\nI TU/101\\JAL bUARA.tJTEE ~\"l) AtJ;\\ E~ PAR.TE RI\\MZ~ I 4:14 ~.1/.\nJd :1!10 1 l!l ~ (TEX. \\ q{og) (''THE PURPnSE [)~ TI~E WRIT tl F\n l-iABEA~ CORPuS I~ TO OBTAirJ A. ~PEEl\\.~ A 1)LfU'~IlATIDtJ\n\nOF A JJE({~DtJS RIGHT fD LigER.A1IOIJ FR/JM ILLEGAl R.EsTR-\n A IJJ T''),\n         -RELA.TbR. l4A.~ ATTA.tHE A. CbPY CiT= J.iiS 1~EtEM.BER D&1\n                                           1\n                                            \\\n\n\n\nd.Dll    1   -~UPPLEMt:rJTAL        t:\\PPL1LA TIOJJ FD~ A Pi:l~f~ C.OJJVILT--\nIDIJ WR.IT OF HABEA~ Lb~PUS A{{TIJ l\\l07t V.A~CL(\\ THErz£-\n\n Fo({f .RELA.Tf)~ R.E&LJE~ T THIS l~DrJ>~ CtJf.J((T TO PLEA~E MAKE\nII             \\t   .\n \"lf\\J&UI({~ !tjTO       THE M~IT E(( OR. I ~StJ E A WRIT CJF MfvJ,)AJiuJ.S\nwrrH TUE MA.N 1\\Ar'£ oF AR-rtc.LE 1LD?,                       vl A. c.c. P.\n                                                RE~PELTFLJLU1 SUBM.11TE•l,\n                                                1>1n.. I)Jt.O.M t. ~1S1Si30\n\n\n\n\nr ·• \\\n\f•\n                               COURT OF CRIMINAL APPEALS OF TEXAS\n                             APPLICATION FOR A WRIT OF HABEAS CORPUS\n                           SEEKING RELIEF FROM FINAL FELONY CONVICTION\n                          UNDER CODE OF CRIMINAL PROCEDURE, ARTICLE 11.07\n\n                                           INSTRUCTIONS\n\n    1.      You must use the complete form, which begins on the following page, to me an\n            application for a writ of habeas corpus seeking relief from a final felony conviction\n            under Article 11.07 of the Code of Criminal Procedure. (This form is not for death-\n            penalty cases, probated sentences which have not been revoked, or misdemeanors.)\n\n    2.      The clerk of the trial court in which you were convicted will make this form\n            available to you, on request, without charge.\n\n    3.      You must file the entire writ application form, including those sections that do not\n            apply to you. If any pages are missing from the form, or if the form has been\n            downloaded and the questions have been, renumbered or omitted, your entire\n            application will be returned as non-compliant. If your application is returned as\n            non-compliant, the clerk of the trial court wiD write a note of the defect on your\n            application and return the form to you without filing it.\n\n    4.      You must make a separate application on a separate form for each judgment of\n            conviction you seek relief from. Even if the judgments were entered in the same\n            court on the same day, you must make a separate application for each one.\n\n    5.      Answer every item that applies to you on the form. You may use additional pages\n            only if you need them for item 17, the facts supporting your ground for relief. Do\n            not attach any additional pages for any other item 17.\n\n    6.      You must include all grounds for relief on the application form as provided by the\n            instructions under item 17. You must also briefly summarize the facts of your claim\n            on the application form as provided by the instructions under item 17.\n\n    7.      Do not cite cases or other law in this application forrn. Do not make legal\n            arguments in this form. Legal citations and arguments may be made in a separate\n            memorandum.\n\n    8.      You must verify the application by signing either the Oath Before Notary Public or\n            the Inmate's Declaration, which are at the end of this form on pages 11 and 12. You\n            may be prosecuted and convicted for aggravated perjury if you make any false\n            statement of a material fact in this application.\n\n    9.      When the application is fully completed, mail the original to the clerk of the\n            convicting district court. Keep a copy of the application for your records.\n\n    10.     You must notify the clerk of the convicting district court Of any change in address\n            after you have filed your application.\n\n\n\n\n    Revised: September I, 2011                                                          ATC-11.07\n\f                                     !LJPPLE ME tJI Al APflLI.C.A TI()rJ.\n                                 EV :1.1\\ EtJ 'l\"IAA.Y     ~E Afb:A.ll':. RI:~U&.S TE•~\n\n                                           Case No . ...,......,-----,----,--\n                                 (The Clerk of the convicting court will fill this line in.)\n\n\n\n                    IN THE COURT OF CRIMINAL APPEALS OF TEXAS\n\n                  APPLICATION FOR A WRIT OF HABEAS CORPUS\n                SEEKING RELIEF FROM FINAL FELONY CONVICTION\n               UNDER CODE OF CRIMINAL PROCEDURE, ARTICLE 11.07\n\n\n.NAME:       9RAKE L~FA.Yern: \\.lilLIS\n.DATE OF BIRTH: _.;..uir~Jl.._YL......Jiu.l.,_\n                                           1 ..LI...~...Q7L...3....____-,----------,---------­\n.PLACE OF CONFINEMENT: CDFF!E U\\ UtJIT- 'fi}Cf-Cr 1\\\n\n.TDCJ-CID NUMBER: _,0._...15....__.__,7.~5'._I3.....0'------- SID NUMBER:\n\n(1)     This application concerns (check all that apply):\n\n        D(      a conviction                                       0         parole\n\n        1M      a sentence                                         0         mandatory supervision\n\n        0       time credit                                        0         out-of-time appeal or petition for\n                                                                             discretionary review\n\n\n(2)     What district court entered the judgment of the conviction you want relief from?\n        (Include the court number and county.)\n\n\n\n(3)     What was the case number in the trial court?\n\n\n\n( 4)    What was the name of the trial judge?\n\n        THE f.IOtJ.   )\n                          I   Rt. f. I< M.A f, N I   ~\n\n\nTl-l7S !S A .!luPPLEM.EtJTAL APPLIC..~Tl.OJ\\l rD 1\"HE DQ!.&.IAJA.l A.PPU.CATt.OAl rtJ\nll.tl1, APPL!..fAiiOI\\1 *'=- WOR-.24D.1D-I(A), PE,j')IJIJ& :£1\\1 THE TR.t~tL LD!JR.i\nAt.JI\\ FI.LE.•~ OtJ .1-11- il1 t1lYIUidtd DIJ .:l\"t.JLY 13, .2.011.\n\n\n                                                             1\n\n\n\nRevised: September I, 2011                                                                            ATC-11.07\n\f(5)     Were you represented by counsel? If yes, provide the attorney's name:\n\n\n\n(6)           ' the date that the judgment was entered?\n        What was\n\n         MAY 11 ,2009\n\n(7)     For what offense were you convicted and what was the sentence?\n\n\n(8)     If you were sentenced on more than one count of an indictment in the same court at\n        the same time, what counts were you convicted of and what was the sentence in each\n        count? ·\n\n\n\n\n(9)     What was the plea you entered? (Check one.)\n\n        o guilty-open plea                o guilty-plea bargain\n        K not guilty                      o nolo contendere/no contest\n\n        If you entered different pleas to counts in a multi-count indiCtment, please explain:\n\n\n\n\n(10)    What kind of tria~ did you have?\n                               \\\n        o no jury                               o jury for guilt and punishment\n\n        ~   jury for guilt, judge for punishment\n\n(11)    Did you testify at trial? If yes, at what phase of the trial did you testify?\n\n         Ye)- t;u:r t T      IAINO l F:AIC E\n\n(12)    Did you appeal from the judgment of conviction?\n\n        til yes                          o no\n\n\n\n\n                                                  2\n\n\nRevised: September I, 2011                                                              ATC-11.07\n\f        If you did appeal, answer the following questions:\n\n        (A)     What court of appeals did you appeal to? ~!F1H                               •XL.srA:tC.r- ~AU A~\n        (B)     What was the case number?             ...~o.O£.i,5J....:..:...JOL9:J...-~Ou.O.u)L..tl0l...:.7.L..--~C:..!J~..___ _ _ _ _ _ __\n\n\n        (C)     Were you represented by counsel on appeal? If yes, provide the attorney's\n                name:\n                IKE l=IQ,J., bEBORAH J:A.Rt!J.S 1 5TA'IE BAA. l:t: D(oS43jOo\n\n        (D)     What was the decision and the date of the decision? fo.EF!A.M.E•}-b- .2~- 1()\n\n(13)    Did you file a petition for discretionary review in the Court of Criminal Appeals?\n\n        o yes                             Ill   no\n\n        If you did _file a petition for discretionary review, answer the following questions:\n\n        (A)     What was the case number?\n\n        (B)     What was the decision and the date of the decision? _ _ _ _ _ _ _ __\n\n(14)    Have you previously filed an application for a writ of habeas corpus under Article\n        11.07 of the Texas Code of Criminal Procedure challenging this conviction?\n\n        • yes     AI:J. 1Ill              o no\n\n        If you answered yes, answer the following questions:\n\n        (A)     What was the Court of Criminal Appeals' writ number?._ _ _ _ _ _ __\n\n        (B)     What was the decision and the date of the decision? _jPuE;o.llr.JL:.•lul:.J!AoJJJC:z..:r_ _ _ __\n\n        (C)     Please identify the reason that the current claims were not presented and\n                could not have been presented on your previous application.\n\n                 THIS        I&   A SUPPI EM.EMIA.L APPliCATION T{) GAn E A,( AAhi:-\n\n                 TOI\\.IA.l ClA.INl..       nuE TD THE APPL:C.ftWI'S IMEtPERtiJJCE IiJ\n\n                 HE ~~r·\\ /JOT RECobAJz.z.E -rHe C.tA:tt~t Rr:ztJ!3 PREjfAJfE,I rtJ na:s\n\n                 ~UPPLEM.E/\\JTAL         APPL'! C.AT ID,J.\n\n\n\n\n                                                       3\n\n\nRevised: September 1, 2011                                                                                                     ATC-11.07\n\f(15)    Do you currently have any petition or appeal pending in any other state or federal\n        court?\n\n        )!(   yes                        o no\n\n        If you answered yes, please provide the name of the court and the case number:\n\n\n\n\n(16)    If you are presenting a claim for time credit, have you exhausted your\n        administrative remedies by presenting your claim to the time credit resolution\n        system of the Texas Department of Criminal Justice? (This requirement applies to\n        any final felony conviction, including state jail felonies)\n\n        o yes                            o no\n\n        If you answered yes, answer the following questions:\n\n        (A)         What date did you present the claim? - - - - - - - - - - - - - - -\n\n        (B)         Did you receive a deCision and, if yes, what was the date of the decision?\n\n\n\n        If you answered no, please explain why you have not submitted your claim:\n\n\n\n\n(17)   Beginning on page 6, state concisely every legal ground for your claim that you are\n       being unlawfully restrained, and then briefly summarize the facts supporting each\n       ground. You must present each ground on the form application and a brief\n       summary ofthe facts. lfyour grounds and brief summary of the facts have not been\n       presented on the form application, the Court will not consider your grounds.\n\n\n\n                                                   4\n\n\nRevised: September 1, 2011                                                                ATC-11.07\n\f                          If you have more than four grounds, use page 10 of the form, which you may copy\n                          as many times as needed to give you a separate page for each ground, with each\n                          ground numbered in sequence.\n\n                          You may attach a memorandum of law to the form a·pplication if you want to\n                          present legal authorities, but the Court will not consider grounds for relief in a\n                          memorandum of hw that were not stated on the form application. If you are\n                          challenging the validity of your conviction, please include a summary of the facts\n                          pertaining to your offense and trial in your memorandum.\n                                                                             ({.EL~VAtJ\"f                     ~1A1\"f ll~ n.t1\"S\n\n              II. \"\n              1\"\\flPiiC.a.tl+                   1.1AS\n                                                             ..        j\n                                                              dlc!1t.+e.d\n                                                                                         ('\n                                                                                         .roL ,4- Q.\n                                                                                                          h     tl\n                                                                                                                 f.tggra.vll.. h!c!     Se..wo.. I           L ,,\n                                                                                                                                                     As.~a.uh·\n                                                                                                                                                                       f\\\n                                                                                                                                                                     O-r\n\n  J<~ya.tltl ~te.Shay Wif\\Kf:ie.ld                                           1   ApplltflAt'_s tl[ftR..·yfi. U..f Did ~-iep-dll.ug~fifl\n\n  h2. fl2CLf +-e.r (\"B. w'•).                                 thi!.        1tld i c.fiYIVJ t a. II eg~d +ha+ ~ pp I i Cllnt pentH rated\ns.w.\\~ ~e..:tulll Dr~flfl with hi~ fit~gu, fc.R. VDL. lr a+ pgs. j,lL f,\n    ..\ns.w., +es+:Fte.d +h£Lt eJYI one. ac..a.~!ltory A~~JfC.11t1-l- (.\\uLL~d dbiJ/\\ hfs\n ~CL.n+~ • grtlbbe.d htu hafld ar\\d pla.t:ed                                                                         i+ dfl     lo.i~ pen,·~. -(~.r. voL.3 ,tit\npgo ~b).~. B.J,J., .Pur+htU +e.s+:.f:e.d to -twa                                                                                    n+htU   !e~ll~Cd·f. itlddefl·h\nnot o.lle.gt?.d                            :fl +nl!.          :nd,'t.+Mutt• Cin ontt occ.o..s~{oll whUe Shf. pre.~eJJ­\ndllci +o b12.. tl..itee.p, Appl ittut+ ~u11ed doL.Jt\\ he.r ~tlf\\·H., and ~ar+ly\n                                                                                     ;\npu112d down hu ~t;tfl.+:e!l in.d fbtJthe.d htU ~ri va.fe. ~tlrf wNh ht..s\nfit~g8ro                  (~.r. VDLe 1,                                11+    (),9.S, 5~--$\"q), Dt1                                  llf\\Dthe.r         DC.C..a..~s,•utll\n\nA.ppl; tll.r'lt -co. lYle.                                   :n+D             c.~... b!ld roo#l .she.. ~ha.re.d w:th h/U ~ts+u~                                  1   and\nPulled                down                      ht2.r        ·Pc.tfli-~          and                 touc.hed               +hi ~rHidt         dild    oub;de. of\nher           p·r ~vcd·e. ~a.r+5 • ( 5, r:. Vlll~~ 31 a+ pgs. 63- 'L/ L\n...\n , -   ~~     -   -   -   '~-     -    -    -    -- -         -    -   -·- -     -   -        -. -   - - .- -    ·- -   -     I .   I\n  •       l.. ~.              1       re.fus +o                   +he. one               VDJume. Dt C.J~rl« fil!lllrd.s.\n       tf f               \"                                                      .                                             I\nl.       ~.       F, ,            refe.r5               +o        +hi!       t:nur+             Rll~Drte.r'..s              nD+es,.\n\n\n                                                                                                      5\n\n\n        Revised: September I, 20I I                                                                                                                       ATC-11.07\n\f                                         ~uPPLE   M.EAJTA.L   C.l~I..M\n\n\n\nNgbHMl                  ttJAIJ'&JI\\ ~ ·~A.T HI~ TR.:t~L C/)WJSE L fl~l~ER£•\\ .IN~FI=ft:.TZVE\nA~SlSTAtJC.E 1          WHERE C..btuJSE l •\\:r1} NOT RE&UE.ST A. CHAR(,E OtJ TUJ: les~Et:l\nXtJ~Lui\\t::l\\ D~~fr.JtE I'J~ IAJ•\\EC..f.AIL~ wz·r!4 A. ti-JzL•' t!Y .:iE~uAt. ffi!JrAtT,\n~R~§~BiPb'fH~etJdkb~J~N~~~ggravtl+ed ~t2'i.ual AHI1Uif ot ll ehfld'\n+be :ndic±dlen+. a.Heged ±haJ Applicao+   pwe±ra.+ed ±he !>etua.t\nDcga.o of 1-he c.hiid wi+h b:~                    £tl\\ger. {[, R. vaL,   1,   a+   -pgs, J!s),\n i)ur~Dg +rial           +he   c.hild compla.lllatlf 1 n.foe ,ve4'rnld k•'Yillltl 6resllliy\n\nbrinKtiled  fs.v.) 1 +o+: £,'ed +bar A.pplicaf\\+ ca.use.d her ba.od to\nfrwc.h his paais. Js . F. \\lfJL. 3J 1.1± p9s. 5r2-tzA). Or1 +wo rHW\n separa.+e oc.cassioll no+ a.tleged :a fhe :na:e.+mea+J Ap_pi:c.ao+\n                                     1\n\n\ntouched her priva.te par+s w:±h his h1111d, Ls.F. VQL, 31 a+ pgS,f,t-\n iOB)., Appl:c.ao+ :s            s.w.)s s!ep-fa:+ber. tlurL'\\9 h.·s -tcl,d Appl.'co11f\n                                                                                   '\nadm:±+ed he had                 on ,,cc.ass~'ot'l ±ooched ·B.w. 1s aod her ymmgtr\ns:bl:ngs' ~r!va.±e pt1r±S through. ±heir tlo±b;ttlg whfie. they Jlepted,\nbecause +h.e\" were. cbroalc bed we++ec.5 1 +a Make. sora fhev were.\n                    }                                   .                                I\n\n\n\n\nn(2± ·we±• Applie.a.n± fur+her fQr,f;t;:ed thed he was B.W.'s o.nd\nher    ~rbflll9.S'       primary         c.11re   glvtr wh:te +heir mo+ber             wort<adJ\noc a++ ended school, (),F. VoL. .3, a± pgs. IU-L'lo). AppVeaaf +est;-\n£,'ed +ha.t on one occ.a.ss:otl B.w. 1 had c.ompta.:ned +hat                             whe11   she\nused +he         res.froom her pci ya +e par+ htu±1 and +ba.+ be ex'ClNI•10ed\n herq ·~ur: \"9 ±he tY-am: (l a.+,too he_ +rwc he d ber pri va.+e pa.rf, fs. f. VoL.\n3J a..+ pg~. !J.ll:J- .QoS L ~ec.tui5e ~Yldtee.t'lty wf.+h fL Ll-!fld by .io_~uo.l\nton+ti.t+ Dr fl'luth t19 ;s, a l2.ss e.r ;(JtltJdeJ ofFea~e tlf ag9ravo..--1-eJ\n                                1c\n\n\n                         t..OtJT IAlu E 1~ CIJ A TT AC.J-IE•\\ PA6E AIUM.I!E.RE•~ 13\n\n\n\n\n                                                    6\n\n\nRevised: September I, 20 II                                                             ATC-11.07\n\fGROUND TWO:\n\n\n\n\nFACTS SUPPORTING GROUND TWO:\n\n\n\n\n                               7\n\n\nRevised: September I, 2011         ATC-11.07\n\fGROUND THREE:\n\n\n\n\nFACTS SUPPORTING GROUND THREE:\n\n\n\n\n                                 8\n\n\nRevised: September I, 2011           ATC~ll.07\n\fGROUND FOUR:\n\n\n\n\nFACTS SUPPORTING GROUND FOUR:\n\n\n\n\n                                9\n\n\nRevised: September 1, 2011          ATC-11.07\n\fGROUND:\n\n\n\n\nFACTS SUPPORTING GROUND:\n\n\n\n\n    WHEREFORE, APPLICANT PRAYS THAT THE COURT GRANT APPLICANT\n        RELIEF TO WHICH HE MAY BE ENTITLED IN THIS PROCEEDING.\n\n\n\n\n                                10\n\n\n\nRevised: September I, 20 II                               ATC-11.07\n\f                                             VERIFICATION\n\n         This application must be verified or it will be dismissed for non-compliance. For verification purposes, an\napplicant is a person filing the application on his or her own behalf. A petitioner is a person filing the application on\nbehalf of an applicant, for example, an applicant's attorney. An inmate is a person who is in custody.\n\n         The inmate applicant must sign either the \"Oath Before a Notary Public\" before a notary public or the\n\"Inmate's Declaration\" without a notary public. If the inmate is represented by a licensed attorney, the attorney may\nsign the \"Oath Before a Notary Public\" as petitioner and then complete \"Petitioner's Information.\" A non-inmate\napplicant must sign the \"Oath Before a Notary Public\" before a notary public unless he is represented by a licensed\nattorney, in which case the attorney may sign the verification as petitioner.\n\n         A non-inmate non-attorney petitioner must sign the \"Oath Before a Notary Public\" before a notary public\nand must also complete \"Petitioner's Information.\" An inmate petitioner must sign either the \"Oath Before a Notary\nPublic\" before a notary public or the \"Inmate's Declaration\" without a notary public and must also complete the\nappropriate \"Petitioner's Information.\"\n\n\n\n\n                                       OATH BEFORE A NOTARY PUBLIC\n\nSTATE OF TEXAS\n\nCOUNTY OF-----~\n\n\n         _ _ _ _ _ _ _ _ _ _ _ _ _ _ _ ,being duly sworn, under oath says: \"I am the applicant I petitioner\n\n(circle one) in this action and know the contents of the above application for a writ of habeas corpus and, according\n\nto my belief, the facts stated in the application are true.\"\n\n\n\n\n                                                          Signature of Applicant I Petitioner (circle one)\n\n\nSUBSCRIBED AND SWORN TO BEFORE ME THIS                              DAY OF _ _ _ _ , 20_\n\n\n\n                                                          Signature of Notary Public\n\n\n\n\n                                                               11\n\n\n\nRevised: September I, 20 II                                                                                  ATC-II.07\n\f..\n\n\n\n                                          VERIFICATION\n          (Complete EITHER the \"oath before a notary public\" OR the \"inmate's declaration.\")\n\n\n                                  OATH BEFORE NOTARY PUBLIC\n\n     STATE OF TEXAS, COUNTY OF _ _ _ _ _ _ _ __\n\n     _ _ _ _ _ _ _ _ _ _ ,BEING FIRST DULY SWORN, UNDER OATH, SAYS:\n\n     THAT HE/SHE IS THE APPLICANT IN THIS ACTION AND KNOWS THE CONTENT OF\n\n     THE ABOVE APPLICATION AND ACCORDING TO APPLICANT'S BELIEF, THE FACTS\n\n     STATED IN THE APPLICATION ARE TRUE.\n\n\n\n\n                                            Signature of Applicant\n\nSUBSCRIBED AND SWORN TO BEFORE ME THIS _ _ DAY OF _ _ _ _ _ _ __\n\n\n\n                                          Signature of Notary Public\n\n\n\n\n                                        INMATE'S DECLARATION\n\n     I,   OYlAI<E LAF'Alf€77£ ldZLII_5                                  , BEING PRESENTLY\n     INCARCERATED IN           Alll1£t.. so.tr! (JJ(IAI7cf                      , DECLARE UNDER\n     PENALTY OF PERJURY THAT, ACCORDING TO MY BELIEF, THE FACTS STATED IN\n     THE APPLICATION ARE TRUE AND CORRECT.\n\n\n     SIGNED ON         IJ.. -()8- .AOII\n\n      fuwu~~n,t_~\n               Signature of Applicant\n\n\n\n                                                    11\n\n\n     Misc. Docket No. 06-103                   Page 12 of 13                   ATC 11.07 (Rev. 03-05-07)\n\f \"\n       •\n...\n\n\n\n\n                     Signature of Attorney\n\n      Attorney Name: _ _ _ _ _ _ _ _ _ _ _ _ __\n\n      SBOT Number: _ _ _ _ _ _ _ _ _ _ _ __\n\n      Address:\n\n\n\n\n      Telephone:\n\n\n\n\n                                                      12\n            Misc. Docket No. 06-103          Page 13 of 13   ATC 11.07 (Rev. 03-05-07)\n\f'     '      .\n\n\n\n\n     S~ua.f - fl.{Sll.u It t:lt'         t1.   t:h~id by -p~rliH·rll.··Htlll c·t -+he. C.hlldls .Se'iua..l\n     wt+h +he.. r~l\\ger I +he. e.v: de-nelL a.ddut.e.d dodl\\g ~p~l :lan+ tr: a I                  s\n     wa.~ .~uf.P:c.~e.n+ +o Wfl.rflln+ t1. c.na.rgtL {')f\\ '':nde.tlUie..y wtfh a C.h:ld\n     by ~e..'tu4-1 ton+Llt+. A~plilat'lt~ +ri£LI tDrJt\\sel.ti.td not re4ut.s+\n    1-ha..t +he. jury be. th£tr9ed                 011     ~tlde.t.e.f\\t y   wt+h    ll. t~iid   by, .Se:itltl.l\n    C.tm+ll.tt ~ or re.ope~+ +he Jury be. c..har9e.d                         \"ll any     fe..~se.r offut..$ fL.\n\n    Alor d:d +h£ tried c.ovr+ sua.. .spot\\+e. c.t-.o.r9e.                    oil   a. lt.Her tlffe.(l5e.\n    ·rHE RE LE VMT ~IA1EMEJJ1 1.11=' FA.Cf~ fhJ PA&E AftJ~~EJt ~\"'1.VE. OF 11-11.S\n    APPL!C.A.TI.O.AJ AA.E IAIC.OA.PORA.TE•\\ A5. PART OF IHE ~UPPoR.T:tJJ& J:\"A£15 Fi'R.\n    Tt(IS .SUfJPlEME:I\\IiAL C.LA.rN\\.e\n\n                                          E\\11. r\\ EJJ T 1-'. R. '{ Hf.AR.:t.N (, RE &lJ f S1\"\n                                           .                             I\n\n\n          :Applic.a.nf     Jubmt+~      +ha.t +hEYe iS 11 ntud Por,-1-hll.                 .fvr~her de.v~lt)~-\n\n    M.EtJr O.f +he. fO..tA·5        re.le.Vlltl+   to hiS .(U~ple.t1IO.fl.jaJ c.lll•th1 b~ ~'l'dl:Ne..t­\n\n +lve. a.5s,'.s+ante. bf C{)tJAJ~e.IJ t1tld rellJ!e.!f~ thcd· +h;~ tour+ \\JOUid\n CJrd~r           +ho..+ a..n e_vidfYlt;ary hidrfllB be_ toll.dm:+ed9 Fvf.fhllr, Appli-\nta.t~+           opplHe. +-11e.   de.ve.loptt~M+     D.P    +h~ PL1d·~       via    tlr'l ll.~f;dllvi+'    beeau.se\nt1 f.'f i   d 11 v; +s c.a n no+ be c. ross- 2-ill.m: n~d,\n\n\n\n\n                                                           - ts-\n\f       EXHIBIT NO. 1\n   \\\n\n\n       \\\n\n       EXHIBIT NO. 1\n\n\n\n\n       EXHIBIT NO. 1\n\n\n\n\n       EXHIBIT NO. 1\n\n\n\n\n       EXHIBIT NO. 1\n\n\n\n\n       EXHIBIT NO. 1\n\n\n\n\n       EXHIBIT NO. 1\n\n\n\n\n       EXHIBIT NO. 1\n\n\n\n\n(cc)\n\f                                        ------~----------~------------------------~-·-·---·-~---·-----------------------~--·\n\n\n\n\nFR0'-'611\n            Drake L. Willis ~ 1575130\n            Coffield Unit-TDCJ-CID\n            2661 FM 2054\n            Tennessee Colony, Texas\n            Zip 75884\n\n   '1'0:\n            TBE J'US'l'ICES OF \"l'HE COURT OF CRIMINAL AP.PEAtS\n            PoOo Box 12308, Capitol Station\n            P.O. Box l23CS\n            Austin, Texas 78711\n\n            RE:\n                   EXPARTE DRAKE L. WILLIES, from D~llas County:\n                   Tri.el Court 'Writ No ... ·N-0&-24020-A\n                   T.C. Cause No. FOS-~4020-T\n\n                                                            LETTER MOTION REQUESTING LEAVE TO\n                                                         FILE A PETITION ~OR A WRIT OF MANDAMUS\n\n\n            The Hon., t6uise Peaison, Clerk:\n            r\"·\"'-··~   ....'11    ...· - ...   _.,   _ _ _ ....   ...   _,r._.,..;._...   ~~~-.   .....   ,...._ot.__,_   ,_t.-..-•   --        'ltall\"\"'O'Idl~~t=h      0        ~.1'\\'\"1'1   .t-\n            ~CIU..LU               }\"VU         f-I.S.C\"QQ't:      .LII._V,_.UI            '-\"lTV          \\w\\,;I'A&. '-   '-11Q\\oo    '-\"1-&    U£.:1\\.al&i.:II\"APti!h   \\ill .   .C.v.-.•r    \"\"''\n            the                   above               numbered\n                               cause of action1 that I submitted a SUPPLE-\n            MEN1'AL                A POST-CONVICTION \\iRI'l' · OF HABEAS, to\n                                          APPLICATION                             FOR\n            the Clerk of the trial court for filing. It h~& been more than\n            45 days since the submission date, and the trial court has not\n            made a Findings of Fact ~oncl~sion Of L~w, on the ORIGinAL o~\n            SUPPLEMENTAL APPLICATION                                                         ~s            is required· by ART. 11.07,                                               V·AoC.C~P~,\n            ~nd of the date of the submission o~ this LETTER MOTION RmQUESTING\n            LEAVE TO PILE A PETITION FOR WRI~ 6~ HABEAS COR?USr l have nbt\n            been notified. that the Original and Supplemental Applications\n            h~ve                   been               transmitted                             to the Court of                                   C~iminal                  Appeals aa man-\n            ;:J;;~ted              by law.                                                                                                             ·\n\n           Would you please request that th~ Court make inquiry in~o\n              matter, or in the alternative grant leav~ to file a Petition\n            the\n        .For A Writ Of Mandamus.\n\n                                                                                                                                  Sincer~ly\n\n\n\n   cc:\n            The Hon., Gary Fitzsimmons, District Clerk\n                Frank Crowley Courts Building\n                133 No Riverside Blvd. LB 12\n                        Dallas, Texas 75207-4313\n\f       EXHIBIT NO. 2\n\n\n\n\n       !EXHIBIT NO. 2\n\n\n\n\n       EXHIBIT NO. 2\n\n\n\n\n       EXHIBIT NO. 2\n\n\n\n\n       EXHIBIT NO. 2\n\n\n\n\n       EXHIBIT NO. 2\n\n\n\n\n       EXHIBIT NO. 2\n\n\n\n\n       EXHIBIT NO. 2\n\n\n\n\n(cc)\n\f                                                              MAY 9, 2012\n\n\n            .FROM:\n                     Drake L. Willis ~ 1575130\n                     Coffield Unit-TDCJ-CID\n                     2661 FM 2054\n                     Tennessee Colony, Texas\n                     Zip 75884\n\n              TO:\n                     THE JUSTICES OF\n                     THE COURT OF CRIMINAL APPEALS\n                     P.o; Box 12308, Capitol Station\n                     Austin, Texas 78711\n\n                     RE: APPLICATION FOR A WRIT OF MANDAMUS IN.EXPARTE.DRAKEI WR-77,246-01\n                         TRIAL CotJR'l' CAUSE NUMBER FOS-24020, I'N THE DISTRICT COURT OF\n                         DALLAS. COUNTY.\n\n                                            LETTER APPLICATION FOR ISSUANCE OF\n                                                    A WRIT OF MANDAMUS\n\n\n                       '1'0 THE JUSTICES OF SAID COURT:\n                     Now Comes, DRAKE t. WILLIS, pro-se,- ®Relator\" in the above numbered .\n                     and     styled cause        of     action, and respectfully shows good cause\n                     for     the issuance        of     a writ of mandamus. Hereinsupport Relator\n                     will show that on MARCH 21, 2012,-this Court in a written ORDER\n                     directed the Dallas County District Clerk (Respondent's Court's\n                     Clerk) in,ihe matter.oi:the ~p~ii~at{on for writ of-habea~ corpu~ ·\n                     filed ·iri EXPAR'l'E DRAKE WR~77,246-:-01, to f.ile a response to Relator's;.\n                     applicat:iol}. for a writ of mandamus _wi__thin 30 days_9f the_Court's\n;   ·,. .\n                     MARCH 21, 2012,_ Order.'_ More· than                30     days has elasped since the\n                     Court's       order,    and ·Relator         has     not     received notice that the\n                     Respondent       Court's         tlerk     has complied with this Cou~t's March\n                     21, 2012, order. Therefore                Relator requests that the Court would\n                     issue     a    writ    of   mandamus        to     compell the Respondent Court to\n                     comply with the mandate of ARTICLE 11.07 V.A.c.c.P. (See Court's\n                     March 21, 2012 ORDER).\n                                                                      ·Respectfully Submitted\n\f       EXHIBIT NO. 3\n\n\n\n\n       EXHIBIT NO. 3\n\n\n\n\n       EXHIBIT NO. 3\n\n\n\n\n       EXHIBIT NO. 3\n\n\n\n\n       EXHIBIT JNO. 3\n\n\n\n\n       EXHIBIT NO. 3\n\n\n\n\n       EXHIBIT 1!10. 3\n\n\n\n\n       EXHIBIT NO. 3\n\n\n\n\n(cc)\n\f       EXHIBIT NO. 4\n\n\n\n\n       EXHIBIT NO. 4\n\n\n\n\n       EXHIBIT NO. 4\n\n\n\n\n       EXHIBIT NO. 4\n\n\n\n\n       EXHIBIT NO. 4\n\n\n\n\n       EXHIBIT NO. 4\n\n\n\n\n       EXHIBIT NO. 4\n\n\n\n\n       EXHIBIT INfO. 4\n\n\n\n\n(cc)\n\f          ~\n::- •.        '__..-....;.J\n                                                 TEXAS DEPARTMENT OF CRIMINAL JUSTICE\n                      (\n                                                   THE OFFICE OF THE GENERAL COUNSEL\n                                                      INTER-OFFICE COMMUNICATION\n\n\n          TO:.                Willis, Drake                                               DATE: September 10,2014\n                              TDCJ # 1575130\n                                                                                          UNIT: Coffield Unit\n\n          FROM: TDCJ - Office of the General Counsel                                      SUBJECT: Correspondence\n\n\n\n         This is in response to your recent letter to:        Legal Affairs (Leonard Peck)                           Dated: _ _ _-\"'S\"'lep\"'-'t\"\"em\"-'--\"'be\"\"r--\"2,_,.=:2_,_0\"-14,____ __\n\n         _ _ _ _ Your correspondence received by this office relates to the\n         above litigation and will be forwarded to the Office of the Attorney\n         General representing the Agency.                                                        ::-:---:-::-:-Issues related to education should be directed to the Windham\n                                                                                                 School Principal on the unit. Continuing Education issues should be sent\n          ::-::::--:---.Your letter is being returned unanswered pursuant to TDCJ                to the Windham School District, P.O. Box 40, Huntsville, TX 77342.\n         Offender Orientation Handbook which states, in part, \"You should\n         always try to solve your problem with staff on your unit or facility before             -:-:----:_Issues related to your commissary account, should be\n         VQ!! submit your grievance.          Always submit your original to the                 directed to: Local Funds, P.O. Box 99, Huntsville, TX 77342-0099.\n         grievance investigator on your facility, and if you appeal a decision to                Issues related to commissary purchases should be directed to the Unit\n         the next level, you must always submit your appeal with the original                    Commissary Supervisor.                  ·\n         Step 1 to the grievance investigator on your facility.\" Resubmit your\n         appeal to the grievance investigator on your unit.                                      ...,.,----Issues related to your Inmate Trust Fund account should be\n                                                                                                 directed to: E & R Programs, Inmate Trust Fund, P.O. Box 629,\n         ::-:--:-----c:Every effort is being made to process grievances within the time          Huntsville, Texas 77342-0629.\n         limits outlined in the Offender Grievance Procedure. For information\n         regarding your grievances, you should contact: Offender Grievance                      =---:-- Your       request for Protective Custody/ Safekeeping/Unit\n         Procedure, P.O. Box 99, Huntsville, Texas 77342-0099.                                   Transfer, due to LIFE ENDANGERMENT has been received by this\n                                                                                                 office, and was immediately forwarded to the appropriate staff for\n         _ _ _ _If you have a complaint or allegations to be made relating to                    immediate investigation and action on your behalf.\n         staff misconduct (i.e., verbal harassment, acts of discrimination, etc.)\n         they should be directed to the Unit Warden or designee.                                 _ _ _ _ Issues related to meals, sack lunches, special diet menus, etc.,\n                                                                                                 are not appropriate for handling by this office. Send an I-60 to the Food\n         --:-:--:--If you have a complaint or allegations to be made relating to                 Service Manager so they may take immediate action regarding your issue.\n         staff misconduct (i.e., excessive UOF; acts of retaliation;) or any                     If this proves to no avail, you may contact: Asst. Director of Food\n         crime committed by offender/employee on State property they should                      Service, P.O. Box 99, Huntsville, TX 77342-0099. Requests for\n         be directed to the unit Office of Inspector General investigator or contact             religious meals should be sent to the Unit Chaplain.\n         the Office of Inspector General, Investigations Division, P.O. Box 99,\n         Huntsville, Texas 77342-0099.                                                          _ _ _-,-The unit physician is the primary care provider at the unit\n                                                                                                level and is responsible for the determination of medical treatments,\n         -,----,-...,-Issues related to time calculations, sentencing, concurrent               medical restrictions, and scheduling services. You should. attempt to\n         time/stacked time, jail time, forfeited good conduct time, back-dated good             resolve your problem on the unit level first by contacting the unit medical\n         conduct time, class, promotion, etc., should be directed to the                        administrator, in writing, for assistance. Subsequently, if you are not in\n         Classification Records Office, Time Section, P.O. Box 99, Huntsville,                  agreement with his/her response you can write to the Patient Liaison\n         Texas 77342-0099.                                                                      Program, Health Services, P.O. Box 99, Huntsville, TX 77342-0099.\n\n         _ _ _ _The TDCJ-CID has policies and procedures in effect for                              X         Issues related to legal assistance should be directed to State\n         processing an offender:s request for an inter-facility transfer. You                   Counsel for Offenders, Legal Services Section, P.O. Box 40Q5,\n         should contact the Unit Chief of Classification and/or Administrative                  Huntsville, TX 77342-4005. Law library issues, legal visits with other\n         Segregation Committee so your request can be processed. The committee                  offenders, etc., should be addressed to Access to Courts at P.O. Box 99,\n         will give careful consideration to the request, and appropriate action will            Huntsville, TX 77342-0099.                               ·\n         be taken. The State Classification Committee makes the final decision.\n                                                                                                _ _ _ _The information presented in your letter is inappropriate for\n         ---:-:-,-·AnY issue related to religious programs, services, holidays,                 handling by this office. Direct your correspondence to the appropriate court\n         or activities should be directed· through the Unit Chaplain or the TDCJ                I state department I or agency responsible for reviewing your concerns.\n         Chaplaincy Department, P.O. Box 99, Huntsville, Texas 77342-0099.\n\n         _ _ _ _ Parole related issues should be directed to the Unit\n         Institutional Parole Officer or contact 'the Board of Pardons & Paroles or             ADDITIONAL COMMENTS:\n         Parole Division, 8610 Shoal Creek Blvd., P.O. Box 13401 Capitol\n         Station, Austin, TX 78711.\n\n         -----\"X..__Public Information Act Section 552.028(a)(l), Texas\n         Government Code provides: \"A governmental body is not required to\n         accept or comply with a request for information from an individual who\n         is imprisoned or confined in a correctional faCility.\"\n\f    iP-utK\nJ             lfllt!L                    TEXAS DEPARTMENT OF CRIMINAL JUSTICE- INSTITUTIONAL DIVISION\n\n                                                        INMATE REQUEST'TO OFFICIAL\n    REASON FOR REQUEST: (Please                     chec~ on~)\n\n    PLEASE. ABIDE BY THE FOLLOWING CHANNELS OF COMMUNICATION. THIS WILL SAVE TIME, GET YOUR REQUEST; TO THE\n    PRQ~ER\n      ...... ..\n                .PERSON, AND GET AN ANSWER TO YOU MORE QUICKLY.\n          {.. :~~\n\n                                                       -                                                                              /\n\n    1.    0 .Unit· Assignment,          Transfer (Chairman                                5.   0   Visiting List (Asst. Director of   ssification, Administration\n              · .iAdtffin'istration Building)                                                      Building)\n         ~,?-;:~~,:;.:, /( -• .: -_\n    2.    0 Rest~r~tio~ of Lost overtime (U          1t Warden-if approved, it            6.   0                           nd related information (Unit Parole\n                    will be forwarded to the State isciplinary Committee)\n\n    3.    0         Request for Promotio in Class or to Trusty Class                      7.   0   Inmate Pris' Record (Request for copy of record, infor-\n                    (Unit Warden- if aP.pr:. ved, will be forwarded to the Director                mation o arole eligibility, discharge date, detainers-Unit\n                    of Classification)                            TDCJ-QGC                         Adf!Jini ratiqn)\n\n                    Clemency- rdon, parole, earlyout-mandatO~WJ~iOJhl\n    4.    0\n                    (Board o Pardons and Paroles, 8610 ShoiP'6fetM ~lvf:f.l\n                                                                                      4   8. · 0   Pe sonal Interview with a representative of an outside\n                                                                                                   agency (Tre{ltment Division, Administration Building)\n                    Austin exas 78757)\n                                                                HUNTSVILLE\n\n    TO:     7i)~1          LE&AL         AF_f_~~EO!JARA e.Ef..~k,_,_)\n                                                           . . _ _ _.\n                                             (Name and title of official)\n                                                                                                       DATE:      act·-oa~ Jell/\n\f                                                         r·~...._\n\n\n\n\nLiving Quarters:       JJ- ~O_!j__-~__L__   _ _ _ _ __\n\n\n\n\nDISPOSITION: (Inmate will not write in this space)\n\n\n\n\nt\\-1·60 (Rev. 11·90)\n\f                                       TEXAS DEPARTMENT OF CRIMINAL JUSTIC~-\\Ii\\~';/!TUTIONAL DIVISION\n\n                                                        INMATE REQUEST TO OFFICIAL\n.\"   {\n\n\n\n     .REASON FOR REQUEST: (Please check one)\n         .                                                --~...       .\n·PLEASE ABIDE· BY THE FOLLOWING CHANNELS OF COMMU   ATION. THIS WILL SAVE TIME, GET YOUR REQUEST TO THE\n PROPER. PERSON, AND GET AN ANSWER TO YOU MORE   CKLY.\n\n     1:, 0 'unit Assignment, Transfer (Chairman of Clas · cation,                                                     5.     0      Visiting List (Asst. Director of cia\n                  ·Administration Building)                                      -                                                  Building)\n\n     2.      D    Restoration of Lost overtime (Unit    rden-if approved, it                                          6.     0      Parole requirements and· elated information (Unit Parole\n                  will be forwarded to the StateD' iplinary Committee)                                                              Counselor)\n\n     3.      0      Request for Promotio in Class or to Trusty . Class                                                7. ·   0      Inmate Prison   cord (Request for copy of record, infor-\n                 ·-::,(/Jnit Warden- if apJJ. ved, will be forwarded to the Dir~ctor                                                mation on p /e eligibility, discharge date, detainers-Unit\n                    of Classification                                     .     · ·                                                 Administr, wn).\n                                                             ..\n     4.      0    Clemenc -Pardon, parole, early out-mandatory supervision ·                                          8.     0      Pers nat Interview with a representative of an outside\n                  (Boa11 of Pardons and Paroles, 8610 Shoal Creek Blvd.·                                                            agency (Treatment Division, Administration Building)\n                  Au in, Texas 78757)\n\n\n\n     TO:         llAllT MAil ((ooiYl\n                         ·\n                                                     /Me,s,_ doR~i:J)\n                                            (Name and title of official)\n                                                                                                                                           . DATE:       ---t;,O~'t._-~J,\"---\"-'1_____\n                                                                                                                                                                                 ;, t2~1J_L_f-'C._4- - -\n                                                                                               ~.   --\n     ADDREss:            2.~ftt Fhl Mslf;                    TG.tV,Jes:sct!J;{:;,:!.tJ.,..J.Y; TexAS 7~ggy\n                                                                                     ~..,;.\n                                                                                              '~    - .\n                                                                                               : '.;.._\\\n                                                                                                                 \"'\n                                                                                                           .:.:.,-r.~\n                                                                                                                                                     '       '\n\n                                                                           ;__   --\\~--:-. ~~:.a                             -:t4. ·:__ . __\n\f      Attltcifid T-&o\n                                                                     /J11WI< /j&rf/\n\n                                                            No: .   JS7.£J3t)                      Unit:   C!J\nLiving Quar\\ers:-   __,X'1--~/.....,_,/...L-~\n                        _                    -_,T~·------   Work Assignment:.      T I~\n                                                                                      I t1            111\\~-J----:------\n                                                                                              JIJ,., AJ\n                                                                                             1f1!,i.J., ..:lo,t ~{)'1/_______.:__ __\n\nDISPOSITION: (Inmate. will not write in this-space)\n\n\n      t (st. Clerk_ (h~ led                       ~ 12/tz/11\n       No     fYV<...l (    was /&<j\")'\"-d s J i 11 D•uz · 11              ()._   i u.dj ~.\n~,.,. 1,, 1 ..,1 . ~{ -fo /1-g_f:f(,.~~;..J.t.., AJt., 1 Me}ft.Ui~ ~led ;z./1/tt·\n              /fid5          ~ ~\" /~;~ct-fZ1 1 ~-,,e.::?~~~. ...... ~~--\n                                                                                     v-~ ~\n\f                                               ..\n                                               ..\n\n\n\n\n/   -&1-60 (Rev. 11-90)   ::: 1·\\:,·   j '!:\n\f                                                          i\n\n\n                                                      t\n                                  TEXAS DEPARTMENT OF CRIMINAL JUSTICE- INSTITUTIONAL DIVISION\n          •·\n                                                  INMATE REQUESTTO OFFICIAL\nREASON FOR REQUEST: (Please check one)\n\nPLEASE ABIDE·BY THE FOLLOWING CHANNELS OF COMMU ICATION. THIS WILL SAVE TIME, GET YOUR REQUEST TO THE\nPROPER. PERSON, AND GET AN ANSWER TO YOU MORE  CKLY.                   ,...,~, , .\n                                                     ·:\"-\\.:\\. .-;},--\n                                                                 ,,..                              ·-·\n1.    0    Unit Assignment, Transfer (Chairman of Classit'                           5.     D      Visiting tist-(Asst. Director of classificati\n           Administration Building)                                                                Building)     l\n                                                                                                                 I\n                                                                                                                 ,i\n\n\n2.    0        Restoration of Lost overtime (Unit W: en-if approved, it              6.     0      Parole reriv_Yrements\n                                                                                                               ,..,,     and relat       information (Unit Parole\n               will be forwarded to the State Disc· tt;~ary Committee)                             Counselor) .t\n•                                                     I\n\n3.    0        Request for Promotion . Class or to Trusty Class                      7.     0      Inmate Prison Reco (Request for copy of record, infor-\n               (Unit Warden- if appro 'd, will be forwarded to the Director                                         igibility, discharge date, detainers-Unit\n               of Classification) ·                                   -\n                                                                              ·\"''\n\n\n4.    0    Clemenc ardon, parole, earlyout-mandatorysupervision .                    :8:   '\"i:J   Person Interview with a representative of an outside\n           (Boali of Pardons and Paroles, 8610 Shoal Creek Blvd.                                   age   (Treatment Division, Administration Building)\n           A in, Texas 78757)\n\n\n\nTO:   t),JI_T tllAIL P.o0A1 (M.Q)                             MD~)E:,0)_ _ _ _\n                                       (Name and title of official)\n                                                                                                         DATE:        C)4~J.3-.2JJ!t/\n\f",
          "html": null,
          "html_lawbox": null,
          "html_columbia": null,
          "html_with_citations": "",
          "extracted_by_ocr": false,
          "opinions_cited": []
        }
      ],
      "judges": "",
      "date_created": "2016-09-29T06:37:07.699408Z",
      "date_modified": "2016-09-29T06:37:07.926728Z",
      "date_filed": "2015-05-14",
      "date_filed_is_approximate": false,
      "slug": "willis-drake-lafayette",
      "citation_id": null,
      "case_name_short": "Willis, Drake Lafayette",
      "case_name": "Willis, Drake Lafayette",
      "case_name_full": "",
      "federal_cite_one": "",
      "federal_cite_two": "",
      "federal_cite_three": "",
      "state_cite_one": "",
      "state_cite_two": "",
      "state_cite_three": "",
      "state_cite_regional": "",
      "specialty_cite_one": "",
      "scotus_early_cite": "",
      "lexis_cite": "",
      "westlaw_cite": "",
      "neutral_cite": "",
      "scdb_id": "",
      "scdb_decision_direction": null,
      "scdb_votes_majority": null,
      "scdb_votes_minority": null,
      "source": "C",
      "procedural_history": "",
      "attorneys": "",
      "nature_of_suit": "",
      "posture": "",
      "syllabus": "",
      "citation_count": 0,
      "precedential_status": "Published",
      "date_blocked": null,
      "blocked": false
    }
  ],
  "audio_files": [],
  "assigned_to": null,
  "referred_to": null,
  "absolute_url": "/docket/4444308/willis-drake-lafayette/",
  "source": 2,
  "assigned_to_str": "",
  "referred_to_str": "",
  "date_created": "2016-09-29T06:37:07.694328Z",
  "date_modified": "2016-09-29T06:37:07.694360Z",
  "date_last_index": null,
  "date_cert_granted": null,
  "date_cert_denied": null,
  "date_argued": null,
  "date_reargued": null,
  "date_reargument_denied": null,
  "date_filed": null,
  "date_terminated": null,
  "date_last_filing": null,
  "case_name_short": "Willis, Drake Lafayette",
  "case_name": "Willis, Drake Lafayette",
  "case_name_full": "",
  "slug": "willis-drake-lafayette",
  "docket_number": "WR-77,246-10",
  "pacer_case_id": "",
  "cause": "",
  "nature_of_suit": "",
  "jury_demand": "",
  "jurisdiction_type": "",
  "filepath_local": null,
  "filepath_ia": "",
  "date_blocked": null,
  "blocked": false,
  "tags": []
}